linreg_ally/__init__.py
linreg_ally/eda.py
linreg_ally/models.py
linreg_ally/multicollinearity.py
linreg_ally/plotting.py
linreg_ally-0.0.3.dist-info/LICENSE
linreg_ally-0.0.3.dist-info/METADATA
linreg_ally-0.0.3.dist-info/WHEEL
linreg_ally-0.0.3.dist-info/RECORD
