Metadata-Version: 2.3
Name: linreg_ally
Version: 0.0.3
Summary: A package to test linearity assumptions to determine whether a linear regression model is good or not
License: MIT
Author: Paramveer Singh
Requires-Python: >=3.11,<4.0
Classifier: License :: OSI Approved :: MIT License
Classifier: Programming Language :: Python :: 3
Classifier: Programming Language :: Python :: 3.11
Classifier: Programming Language :: Python :: 3.12
Classifier: Programming Language :: Python :: 3.13
Requires-Dist: altair (>=5.5.0,<6.0.0)
Requires-Dist: altair-ally (>=0.1.1,<0.2.0)
Requires-Dist: numpy (>=2.2.2,<3.0.0)
Requires-Dist: pandas (>=2.2.3,<3.0.0)
Requires-Dist: scikit-learn (>=1.6.1,<2.0.0)
Requires-Dist: scipy (>=1.15.1,<2.0.0)
Requires-Dist: statsmodels (>=0.14.4,<0.15.0)
